Workbook

Sheet Raw Data (USD Millions)
A1: BCG X — GFC AI Chatbot Project | 10-K Financial Data Extract (FY2022–FY2024) | All figures in USD Millions
A2: Company | B2: Ticker | C2: FY End | D2: Fiscal Year | E2: Total Revenue | F2: Net Income | G2: Total Assets | H2: Total Liabilities | I2: Cash Flow from Operations
A3: Microsoft | B3: MSFT | C3: June 30 | D3: 2022 | E3: 198270 | F3: 72738 | G3: 364840 | H3: 198298 | I3: 89035
A4: Microsoft | B4: MSFT | C4: June 30 | D4: 2023 | E4: 211915 | F4: 72361 | G4: 411976 | H4: 205753 | I4: 87582
A5: Microsoft | B5: MSFT | C5: June 30 | D5: 2024 | E5: 245122 | F5: 88136 | G5: 512163 | H5: 243686 | I5: 118548
A6: Apple | B6: AAPL | C6: September 30 | D6: 2022 | E6: 394328 | F6: 99803 | G6: 352755 | H6: 302083 | I6: 122151
A7: Apple | B7: AAPL | C7: September 30 | D7: 2023 | E7: 383285 | F7: 96995 | G7: 352583 | H7: 290437 | I7: 113736
A8: Apple | B8: AAPL | C8: September 30 | D8: 2024 | E8: 391035 | F8: 93736 | G8: 364980 | H8: 308030 | I8: 118254
A9: Tesla | B9: TSLA | C9: December 31 | D9: 2022 | E9: 81462 | F9: 12556 | G9: 82338 | H9: 36440 | I9: 14485
A10: Tesla | B10: TSLA | C10: December 31 | D10: 2023 | E10: 96773 | F10: 14997 | G10: 106618 | H10: 43009 | I10: 13256
A11: Tesla | B11: TSLA | C11: December 31 | D11: 2024 | E11: 97690 | F11: 7263 | G11: 122070 | H11: 50521 | I11: 14923
A13: Source: SEC EDGAR 10-K Annual Filings | Microsoft: CIK 789019 | Apple: CIK 320193 | Tesla: CIK 1318605

Sheet YoY Growth & Ratios
A1: BCG X — YoY Growth Rates & Financial Ratios | Formulas linked from Raw Data sheet
A2: Company | B2: Ticker | C2: FY End | D2: Fiscal Year | E2: Revenue Growth % | F2: Net Income Growth % | G2: Assets Growth % | H2: Net Profit Margin % | I2: Debt Ratio | J2: ROA % | K2: OCF/Revenue % | L2: Equity (USD Mn)
A3: ='Raw Data (USD Millions)'!A3 -> Microsoft | B3: ='Raw Data (USD Millions)'!B3 -> MSFT | C3: ='Raw Data (USD Millions)'!C3 -> June 30 | D3: ='Raw Data (USD Millions)'!D3 -> 2022 | E3: - | F3: - | G3: - | H3: ='Raw Data (USD Millions)'!F3/'Raw Data (USD Millions)'!E3 -> 0.36686337 | I3: ='Raw Data (USD Millions)'!H3/'Raw Data (USD Millions)'!G3 -> 0.54352045 | J3: ='Raw Data (USD Millions)'!F3/'Raw Data (USD Millions)'!G3 -> 0.19936959 | K3: ='Raw Data (USD Millions)'!I3/'Raw Data (USD Millions)'!E3 -> 0.44905936 | L3: ='Raw Data (USD Millions)'!G3-'Raw Data (USD Millions)'!H3 -> 166542
A4: ='Raw Data (USD Millions)'!A4 -> Microsoft | B4: ='Raw Data (USD Millions)'!B4 -> MSFT | C4: ='Raw Data (USD Millions)'!C4 -> June 30 | D4: ='Raw Data (USD Millions)'!D4 -> 2023 | E4: =('Raw Data (USD Millions)'!E4-'Raw Data (USD Millions)'!E3)/'Raw Data (USD Millions)'!E3 -> 0.068820296 | F4: =('Raw Data (USD Millions)'!F4-'Raw Data (USD Millions)'!F3)/'Raw Data (USD Millions)'!F3 -> -0.0051829855 | G4: =('Raw Data (USD Millions)'!G4-'Raw Data (USD Millions)'!G3)/'Raw Data (USD Millions)'!G3 -> 0.12919636 | H4: ='Raw Data (USD Millions)'!F4/'Raw Data (USD Millions)'!E4 -> 0.34146238 | I4: ='Raw Data (USD Millions)'!H4/'Raw Data (USD Millions)'!G4 -> 0.49942958 | J4: ='Raw Data (USD Millions)'!F4/'Raw Data (USD Millions)'!G4 -> 0.17564373 | K4: ='Raw Data (USD Millions)'!I4/'Raw Data (USD Millions)'!E4 -> 0.41328835 | L4: ='Raw Data (USD Millions)'!G4-'Raw Data (USD Millions)'!H4 -> 206223
A5: ='Raw Data (USD Millions)'!A5 -> Microsoft | B5: ='Raw Data (USD Millions)'!B5 -> MSFT | C5: ='Raw Data (USD Millions)'!C5 -> June 30 | D5: ='Raw Data (USD Millions)'!D5 -> 2024 | E5: =('Raw Data (USD Millions)'!E5-'Raw Data (USD Millions)'!E4)/'Raw Data (USD Millions)'!E4 -> 0.15669962 | F5: =('Raw Data (USD Millions)'!F5-'Raw Data (USD Millions)'!F4)/'Raw Data (USD Millions)'!F4 -> 0.21800417 | G5: =('Raw Data (USD Millions)'!G5-'Raw Data (USD Millions)'!G4)/'Raw Data (USD Millions)'!G4 -> 0.2431865 | H5: ='Raw Data (USD Millions)'!F5/'Raw Data (USD Millions)'!E5 -> 0.35955973 | I5: ='Raw Data (USD Millions)'!H5/'Raw Data (USD Millions)'!G5 -> 0.47579774 | J5: ='Raw Data (USD Millions)'!F5/'Raw Data (USD Millions)'!G5 -> 0.17208584 | K5: ='Raw Data (USD Millions)'!I5/'Raw Data (USD Millions)'!E5 -> 0.48362856 | L5: ='Raw Data (USD Millions)'!G5-'Raw Data (USD Millions)'!H5 -> 268477
A6: ='Raw Data (USD Millions)'!A6 -> Apple | B6: ='Raw Data (USD Millions)'!B6 -> AAPL | C6: ='Raw Data (USD Millions)'!C6 -> September 30 | D6: ='Raw Data (USD Millions)'!D6 -> 2022 | E6: - | F6: - | G6: - | H6: ='Raw Data (USD Millions)'!F6/'Raw Data (USD Millions)'!E6 -> 0.25309641 | I6: ='Raw Data (USD Millions)'!H6/'Raw Data (USD Millions)'!G6 -> 0.85635356 | J6: ='Raw Data (USD Millions)'!F6/'Raw Data (USD Millions)'!G6 -> 0.28292441 | K6: ='Raw Data (USD Millions)'!I6/'Raw Data (USD Millions)'!E6 -> 0.30977004 | L6: ='Raw Data (USD Millions)'!G6-'Raw Data (USD Millions)'!H6 -> 50672
A7: ='Raw Data (USD Millions)'!A7 -> Apple | B7: ='Raw Data (USD Millions)'!B7 -> AAPL | C7: ='Raw Data (USD Millions)'!C7 -> September 30 | D7: ='Raw Data (USD Millions)'!D7 -> 2023 | E7: =('Raw Data (USD Millions)'!E7-'Raw Data (USD Millions)'!E6)/'Raw Data (USD Millions)'!E6 -> -0.028004605 | F7: =('Raw Data (USD Millions)'!F7-'Raw Data (USD Millions)'!F6)/'Raw Data (USD Millions)'!F6 -> -0.028135427 | G7: =('Raw Data (USD Millions)'!G7-'Raw Data (USD Millions)'!G6)/'Raw Data (USD Millions)'!G6 -> -0.00048759054 | H7: ='Raw Data (USD Millions)'!F7/'Raw Data (USD Millions)'!E7 -> 0.25306234 | I7: ='Raw Data (USD Millions)'!H7/'Raw Data (USD Millions)'!G7 -> 0.82374079 | J7: ='Raw Data (USD Millions)'!F7/'Raw Data (USD Millions)'!G7 -> 0.27509835 | K7: ='Raw Data (USD Millions)'!I7/'Raw Data (USD Millions)'!E7 -> 0.29674002 | L7: ='Raw Data (USD Millions)'!G7-'Raw Data (USD Millions)'!H7 -> 62146
A8: ='Raw Data (USD Millions)'!A8 -> Apple | B8: ='Raw Data (USD Millions)'!B8 -> AAPL | C8: ='Raw Data (USD Millions)'!C8 -> September 30 | D8: ='Raw Data (USD Millions)'!D8 -> 2024 | E8: =('Raw Data (USD Millions)'!E8-'Raw Data (USD Millions)'!E7)/'Raw Data (USD Millions)'!E7 -> 0.020219941 | F8: =('Raw Data (USD Millions)'!F8-'Raw Data (USD Millions)'!F7)/'Raw Data (USD Millions)'!F7 -> -0.03359967 | G8: =('Raw Data (USD Millions)'!G8-'Raw Data (USD Millions)'!G7)/'Raw Data (USD Millions)'!G7 -> 0.035160515 | H8: ='Raw Data (USD Millions)'!F8/'Raw Data (USD Millions)'!E8 -> 0.23971256 | I8: ='Raw Data (USD Millions)'!H8/'Raw Data (USD Millions)'!G8 -> 0.84396405 | J8: ='Raw Data (USD Millions)'!F8/'Raw Data (USD Millions)'!G8 -> 0.25682503 | K8: ='Raw Data (USD Millions)'!I8/'Raw Data (USD Millions)'!E8 -> 0.30241283 | L8: ='Raw Data (USD Millions)'!G8-'Raw Data (USD Millions)'!H8 -> 56950
A9: ='Raw Data (USD Millions)'!A9 -> Tesla | B9: ='Raw Data (USD Millions)'!B9 -> TSLA | C9: ='Raw Data (USD Millions)'!C9 -> December 31 | D9: ='Raw Data (USD Millions)'!D9 -> 2022 | E9: - | F9: - | G9: - | H9: ='Raw Data (USD Millions)'!F9/'Raw Data (USD Millions)'!E9 -> 0.15413322 | I9: ='Raw Data (USD Millions)'!H9/'Raw Data (USD Millions)'!G9 -> 0.44256601 | J9: ='Raw Data (USD Millions)'!F9/'Raw Data (USD Millions)'!G9 -> 0.15249338 | K9: ='Raw Data (USD Millions)'!I9/'Raw Data (USD Millions)'!E9 -> 0.17781297 | L9: ='Raw Data (USD Millions)'!G9-'Raw Data (USD Millions)'!H9 -> 45898
A10: ='Raw Data (USD Millions)'!A10 -> Tesla | B10: ='Raw Data (USD Millions)'!B10 -> TSLA | C10: ='Raw Data (USD Millions)'!C10 -> December 31 | D10: ='Raw Data (USD Millions)'!D10 -> 2023 | E10: =('Raw Data (USD Millions)'!E10-'Raw Data (USD Millions)'!E9)/'Raw Data (USD Millions)'!E9 -> 0.18795267 | F10: =('Raw Data (USD Millions)'!F10-'Raw Data (USD Millions)'!F9)/'Raw Data (USD Millions)'!F9 -> 0.19440905 | G10: =('Raw Data (USD Millions)'!G10-'Raw Data (USD Millions)'!G9)/'Raw Data (USD Millions)'!G9 -> 0.29488207 | H10: ='Raw Data (USD Millions)'!F10/'Raw Data (USD Millions)'!E10 -> 0.15497091 | I10: ='Raw Data (USD Millions)'!H10/'Raw Data (USD Millions)'!G10 -> 0.40339342 | J10: ='Raw Data (USD Millions)'!F10/'Raw Data (USD Millions)'!G10 -> 0.14066105 | K10: ='Raw Data (USD Millions)'!I10/'Raw Data (USD Millions)'!E10 -> 0.13698036 | L10: ='Raw Data (USD Millions)'!G10-'Raw Data (USD Millions)'!H10 -> 63609
A11: ='Raw Data (USD Millions)'!A11 -> Tesla | B11: ='Raw Data (USD Millions)'!B11 -> TSLA | C11: ='Raw Data (USD Millions)'!C11 -> December 31 | D11: ='Raw Data (USD Millions)'!D11 -> 2024 | E11: =('Raw Data (USD Millions)'!E11-'Raw Data (USD Millions)'!E10)/'Raw Data (USD Millions)'!E10 -> 0.0094757835 | F11: =('Raw Data (USD Millions)'!F11-'Raw Data (USD Millions)'!F10)/'Raw Data (USD Millions)'!F10 -> -0.51570314 | G11: =('Raw Data (USD Millions)'!G11-'Raw Data (USD Millions)'!G10)/'Raw Data (USD Millions)'!G10 -> 0.14492862 | H11: ='Raw Data (USD Millions)'!F11/'Raw Data (USD Millions)'!E11 -> 0.074347426 | I11: ='Raw Data (USD Millions)'!H11/'Raw Data (USD Millions)'!G11 -> 0.41386909 | J11: ='Raw Data (USD Millions)'!F11/'Raw Data (USD Millions)'!G11 -> 0.059498648 | K11: ='Raw Data (USD Millions)'!I11/'Raw Data (USD Millions)'!E11 -> 0.15275873 | L11: ='Raw Data (USD Millions)'!G11-'Raw Data (USD Millions)'!H11 -> 71549
A15: Black = formula | Blue = hardcoded input | Source: SEC EDGAR 10-K (Microsoft CIK 789019, Apple CIK 320193, Tesla CIK 1318605)

Sheet Company Summaries
A1: BCG X — 3-Year Financial Summary by Company | FY2022–FY2024
A3: Microsoft (MSFT) — Fiscal Year End: June 30
A4: Metric | B4: FY2022 | C4: FY2023 | D4: FY2024 | E4: FY23 YoY % | F4: FY24 YoY %
A5: Total Revenue | B5: 198270 | C5: 211915 | D5: 245122 | E5: =(C5-B5)/B5 -> 0.068820296 | F5: =(D5-C5)/C5 -> 0.15669962
A6: Net Income | B6: 72738 | C6: 72361 | D6: 88136 | E6: =(C6-B6)/B6 -> -0.0051829855 | F6: =(D6-C6)/C6 -> 0.21800417
A7: Total Assets | B7: 364840 | C7: 411976 | D7: 512163 | E7: =(C7-B7)/B7 -> 0.12919636 | F7: =(D7-C7)/C7 -> 0.2431865
A8: Total Liabilities | B8: 198298 | C8: 205753 | D8: 243686 | E8: =(C8-B8)/B8 -> 0.037594933 | F8: =(D8-C8)/C8 -> 0.18436183
A9: Cash Flow from Operations | B9: 89035 | C9: 87582 | D9: 118548 | E9: =(C9-B9)/B9 -> -0.016319425 | F9: =(D9-C9)/C9 -> 0.3535658
A11: Apple (AAPL) — Fiscal Year End: September 30
A12: Metric | B12: FY2022 | C12: FY2023 | D12: FY2024 | E12: FY23 YoY % | F12: FY24 YoY %
A13: Total Revenue | B13: 394328 | C13: 383285 | D13: 391035 | E13: =(C13-B13)/B13 -> -0.028004605 | F13: =(D13-C13)/C13 -> 0.020219941
A14: Net Income | B14: 99803 | C14: 96995 | D14: 93736 | E14: =(C14-B14)/B14 -> -0.028135427 | F14: =(D14-C14)/C14 -> -0.03359967
A15: Total Assets | B15: 352755 | C15: 352583 | D15: 364980 | E15: =(C15-B15)/B15 -> -0.00048759054 | F15: =(D15-C15)/C15 -> 0.035160515
A16: Total Liabilities | B16: 302083 | C16: 290437 | D16: 308030 | E16: =(C16-B16)/B16 -> -0.038552318 | F16: =(D16-C16)/C16 -> 0.060574238
A17: Cash Flow from Operations | B17: 122151 | C17: 113736 | D17: 118254 | E17: =(C17-B17)/B17 -> -0.068890144 | F17: =(D17-C17)/C17 -> 0.03972357
A19: Tesla (TSLA) — Fiscal Year End: December 31
A20: Metric | B20: FY2022 | C20: FY2023 | D20: FY2024 | E20: FY23 YoY % | F20: FY24 YoY %
A21: Total Revenue | B21: 81462 | C21: 96773 | D21: 97690 | E21: =(C21-B21)/B21 -> 0.18795267 | F21: =(D21-C21)/C21 -> 0.0094757835
A22: Net Income | B22: 12556 | C22: 14997 | D22: 7263 | E22: =(C22-B22)/B22 -> 0.19440905 | F22: =(D22-C22)/C22 -> -0.51570314
A23: Total Assets | B23: 82338 | C23: 106618 | D23: 122070 | E23: =(C23-B23)/B23 -> 0.29488207 | F23: =(D23-C23)/C23 -> 0.14492862
A24: Total Liabilities | B24: 36440 | C24: 43009 | D24: 50521 | E24: =(C24-B24)/B24 -> 0.18026894 | F24: =(D24-C24)/C24 -> 0.17466112
A25: Cash Flow from Operations | B25: 14485 | C25: 13256 | D25: 14923 | E25: =(C25-B25)/B25 -> -0.084846393 | F25: =(D25-C25)/C25 -> 0.12575438
A27: Source: SEC EDGAR 10-K Annual Filings | All figures USD Millions | Blue = input | Black = formula
